netplan/__init__.py
netplan/config.py
netplan/interface.py
netplan/parser.py
netplan/py.typed
netplan_ebs-0.4.1.data/scripts/netplan-parser
netplan_ebs-0.4.1.dist-info/METADATA
netplan_ebs-0.4.1.dist-info/WHEEL
netplan_ebs-0.4.1.dist-info/top_level.txt
netplan_ebs-0.4.1.dist-info/zip-safe
netplan_ebs-0.4.1.dist-info/RECORD
