Metadata-Version: 2.1
Name: netplan-ebs
Version: 0.4.1
Summary: A library for parsing the netplan configuration data
Home-page: https://github.com/ebs-universe/netplan-ebs
Author: StorPool OpenStack development team
Author-email: openstack-dev@storpool.com
License: Apache License 2.0
Keywords: netplan
Platform: UNKNOWN
Requires-Dist: PyYAML
Requires-Dist: typing ; python_version < "3"
